README.md
setup.py
DPConFil/Clump_Class.py
DPConFil/Clump_Class_Funs.py
DPConFil/Filament_Class.py
DPConFil/Filament_Class_Funs_Analysis.py
DPConFil/Filament_Class_Funs_Identification.py
DPConFil/Filament_Class_Funs_Table.py
DPConFil/Plot_and_Save_Funs.py
DPConFil/Profile_Funs.py
DPConFil.egg-info/PKG-INFO
DPConFil.egg-info/SOURCES.txt
DPConFil.egg-info/dependency_links.txt
DPConFil.egg-info/requires.txt
DPConFil.egg-info/top_level.txt