Metadata-Version: 2.1
Name: DPConFil
Version: 0.0.1
Summary: A collection of filament identification and analysis algorithms
Home-page: https://github.com/JiangYuTS/DPConFil
Author: ['Jiang Yu']
Author-email: yujiang@pmo.ac.cn
Keywords: astrophysics,DPConFil,filaments
